firefox_cert_override/__init__.py
firefox_cert_override/base.py
firefox_cert_override/cli.py
firefox_cert_override/utils.py
firefox_cert_override-0.1.1.dist-info/DESCRIPTION.rst
firefox_cert_override-0.1.1.dist-info/METADATA
firefox_cert_override-0.1.1.dist-info/RECORD
firefox_cert_override-0.1.1.dist-info/WHEEL
firefox_cert_override-0.1.1.dist-info/entry_points.txt
firefox_cert_override-0.1.1.dist-info/metadata.json
firefox_cert_override-0.1.1.dist-info/top_level.txt
