Metadata-Version: 2.0
Name: firefox-cert-override
Version: 0.1.1
Summary: Tool for generating cert_override.txt for Firefox profiles.
Home-page: https://github.com/Osmose/firefox-cert-override
Author: Osmose (Michael Kelly)
Author-email: me@mkelly.me
License: MIT
Keywords: firefox certificate security
Platform: UNKNOWN
Classifier: Development Status :: 3 - Alpha
Classifier: Intended Audience :: Developers
Classifier: Topic :: Software Development
Classifier: License :: OSI Approved :: MIT License
Classifier: Programming Language :: Python :: 3.5
Requires-Dist: click
Requires-Dist: pyOpenSSL
Provides-Extra: test
Requires-Dist: pytest; extra == 'test'
Requires-Dist: flake8; extra == 'test'
